duhs/__init__.py
duhs/cli.py
duhs/core.py
duhs-0.1.1.dist-info/licenses/LICENSE
duhs-0.1.1.dist-info/METADATA
duhs-0.1.1.dist-info/WHEEL
duhs-0.1.1.dist-info/entry_points.txt
duhs-0.1.1.dist-info/top_level.txt
duhs-0.1.1.dist-info/RECORD
